.gitignore
.readthedocs.yml
AB_Dor.gif
CITATION.cff
LICENSE
MANIFEST.in
README.rst
example_coords.csv
example_targets.csv
make_gif.py
pyproject.toml
run_tess_cutouts.py
run_tess_sectors.py
setup.cfg
setup.py
todo.list
tox.ini
.github/workflows/tlr_tests.yml
docs/Makefile
docs/api.rst
docs/command_line.rst
docs/conf.py
docs/index.rst
docs/input_parameters.rst
docs/install.rst
docs/make.bat
docs/python_commands.rst
tessilator/__init__.py
tessilator/contaminants.py
tessilator/fixedconstants.py
tessilator/lc_analysis.py
tessilator/makeplots.py
tessilator/maketable.py
tessilator/tess_stars2px.py
tessilator/tessilator.py
tessilator.egg-info/PKG-INFO
tessilator.egg-info/SOURCES.txt
tessilator.egg-info/dependency_links.txt
tessilator.egg-info/entry_points.txt
tessilator.egg-info/not-zip-safe
tessilator.egg-info/requires.txt
tessilator.egg-info/top_level.txt
tessilator/scripts/__init__.py
tessilator/scripts/run_tess_cutouts.py
tessilator/scripts/run_tess_sectors.py
tessilator/tests/__init__.py
tessilator/tests/test_clean_lc.py
tessilator/tests/test_contaminants.py
tessilator/tests/test_cutouts.py
tessilator/tests/ABDor_tests/ABDor_36_4_3_phot_out_fixed.tab
tessilator/tests/ABDor_tests/ABDor_36_4_3_slice0000.fits
tessilator/tests/ABDor_tests/ABDor_36_4_3_slice0386.fits
tessilator/tests/ABDor_tests/ABDor_36_4_3_slice0772.fits
tessilator/tests/ABDor_tests/ABDor_36_4_3_slice1158.fits
tessilator/tests/ABDor_tests/ABDor_36_4_3_slice1544.fits
tessilator/tests/ABDor_tests/ABDor_36_4_3_slice1931.fits
tessilator/tests/ABDor_tests/ABDor_36_4_3_slice2317.fits
tessilator/tests/ABDor_tests/ABDor_36_4_3_slice2703.fits
tessilator/tests/ABDor_tests/ABDor_36_4_3_slice3089.fits
tessilator/tests/ABDor_tests/ABDor_36_4_3_slice3476.fits
tessilator/tests/__pycache__/__init__.cpython-39.pyc
tessilator/tests/__pycache__/test_clean_lc.cpython-39-pytest-7.2.1.pyc
tessilator/tests/__pycache__/test_contaminants.cpython-39-pytest-7.2.1.pyc
tessilator/tests/__pycache__/test_cutouts.cpython-39-pytest-7.2.1.pyc
tessilator/tests/__pycache__/test_gtd.cpython-39-pytest-7.2.1.pyc