Metadata-Version: 2.1
Name: tessilator
Version: 0.1.2
Summary: The one-stop shop for measuring TESS rotation periods
Home-page: https://github.com/alexbinks/tessilator
Author: Alex Binks & Moritz Guenther
Author-email: abinks@mit.edu
License: MIT License
Provides-Extra: docs
Provides-Extra: test
License-File: LICENSE
